aiomultithreading/__init__.py
aiomultithreading/__version__.py
aiomultithreading/pool.py
aiomultithreading/types.py
tests/__init__.py
tests/__main__.py
tests/base.py
tests/test_pool.py
aiomultithreading-0.1.1.dist-info/LICENSE
aiomultithreading-0.1.1.dist-info/METADATA
aiomultithreading-0.1.1.dist-info/WHEEL
aiomultithreading-0.1.1.dist-info/top_level.txt
aiomultithreading-0.1.1.dist-info/RECORD
