Metadata-Version: 2.1
Name: aiomultithreading
Version: 0.1.1
Summary: AsyncIO, threading and multiprocessing combined to created a powerful executor
Author: Vizonex
License: The MIT License (MIT)
Keywords: aiomultithreading,multiprocessing,threading,asyncio
Classifier: Programming Language :: Python :: 3
Classifier: License :: OSI Approved :: MIT License
Requires-Python: >=3.7
License-File: LICENSE
Requires-Dist: aiothreading
Requires-Dist: aiomultiprocess
